{
"meta":{"test_sets":[],"test_metrics":[],"learn_metrics":[{"best_value":"Min","name":"Logloss"}],"launch_mode":"Train","parameters":"","iteration_count":150,"learn_sets":["learn"],"name":"experiment"},
"iterations":[
{"learn":[0.6891667576],"iteration":0,"passed_time":0.00343775902,"remaining_time":0.5122260939},
{"learn":[0.6855784191],"iteration":1,"passed_time":0.006741662687,"remaining_time":0.4988830388},
{"learn":[0.6821624531],"iteration":2,"passed_time":0.0100433694,"remaining_time":0.4921251004},
{"learn":[0.6790335006],"iteration":3,"passed_time":0.01333977021,"remaining_time":0.4869016127},
{"learn":[0.6756870672],"iteration":4,"passed_time":0.01669762681,"remaining_time":0.4842311775},
{"learn":[0.6726009334],"iteration":5,"passed_time":0.01995661137,"remaining_time":0.4789586728},
{"learn":[0.6691297902],"iteration":6,"passed_time":0.0232422084,"remaining_time":0.4748051144},
{"learn":[0.6668224494],"iteration":7,"passed_time":0.02654009418,"remaining_time":0.4710866717},
{"learn":[0.6641253101],"iteration":8,"passed_time":0.02984487983,"remaining_time":0.467569784},
{"learn":[0.6616687962],"iteration":9,"passed_time":0.03358430788,"remaining_time":0.4701803104},
{"learn":[0.658915888],"iteration":10,"passed_time":0.03688702158,"remaining_time":0.4661178181},
{"learn":[0.6565646306],"iteration":11,"passed_time":0.04015469096,"remaining_time":0.461778946},
{"learn":[0.6546868568],"iteration":12,"passed_time":0.04346857243,"remaining_time":0.4580918787},
{"learn":[0.6523610943],"iteration":13,"passed_time":0.04681641523,"remaining_time":0.4547880336},
{"learn":[0.6501156617],"iteration":14,"passed_time":0.05013882553,"remaining_time":0.4512494297},
{"learn":[0.6485671922],"iteration":15,"passed_time":0.05347507755,"remaining_time":0.4478537745},
{"learn":[0.6464434228],"iteration":16,"passed_time":0.05673547808,"remaining_time":0.4438716815},
{"learn":[0.6441841409],"iteration":17,"passed_time":0.06008161691,"remaining_time":0.440598524},
{"learn":[0.6423364185],"iteration":18,"passed_time":0.06332070986,"remaining_time":0.4365796311},
{"learn":[0.6410771934],"iteration":19,"passed_time":0.06653165237,"remaining_time":0.4324557404},
{"learn":[0.637985045],"iteration":20,"passed_time":0.06989811379,"remaining_time":0.4293741276},
{"learn":[0.6365738746],"iteration":21,"passed_time":0.07318541479,"remaining_time":0.4258060497},
{"learn":[0.6355204064],"iteration":22,"passed_time":0.07647572573,"remaining_time":0.4222790073},
{"learn":[0.6331173702],"iteration":23,"passed_time":0.07986439572,"remaining_time":0.4192880775},
{"learn":[0.6312855876],"iteration":24,"passed_time":0.08316293449,"remaining_time":0.4158146724},
{"learn":[0.6292288115],"iteration":25,"passed_time":0.08647507799,"remaining_time":0.4124196027},
{"learn":[0.627369048],"iteration":26,"passed_time":0.08974919825,"remaining_time":0.4088574587},
{"learn":[0.6258473499],"iteration":27,"passed_time":0.09304408309,"remaining_time":0.405406362},
{"learn":[0.6238826603],"iteration":28,"passed_time":0.09630522461,"remaining_time":0.4018252475},
{"learn":[0.6218042638],"iteration":29,"passed_time":0.09953329877,"remaining_time":0.3981331951},
{"learn":[0.620597005],"iteration":30,"passed_time":0.1027866134,"remaining_time":0.3945679677},
{"learn":[0.6192564598],"iteration":31,"passed_time":0.1061512099,"remaining_time":0.3914325865},
{"learn":[0.6171811418],"iteration":32,"passed_time":0.1094932348,"remaining_time":0.3882032871},
{"learn":[0.615442554],"iteration":33,"passed_time":0.1128000764,"remaining_time":0.3848473196},
{"learn":[0.6131609382],"iteration":34,"passed_time":0.1161187738,"remaining_time":0.3815331139},
{"learn":[0.6119969158],"iteration":35,"passed_time":0.1193912171,"remaining_time":0.3780721875},
{"learn":[0.6102902116],"iteration":36,"passed_time":0.1226411788,"remaining_time":0.3745527894},
{"learn":[0.6089366649],"iteration":37,"passed_time":0.1258843467,"remaining_time":0.3710275481},
{"learn":[0.6078408836],"iteration":38,"passed_time":0.1291309805,"remaining_time":0.3675266368},
{"learn":[0.6068866396],"iteration":39,"passed_time":0.1323989019,"remaining_time":0.3640969801},
{"learn":[0.6056284858],"iteration":40,"passed_time":0.1356184722,"remaining_time":0.36054667},
{"learn":[0.6046204156],"iteration":41,"passed_time":0.1389273578,"remaining_time":0.3572417771},
{"learn":[0.6035034939],"iteration":42,"passed_time":0.1421771055,"remaining_time":0.3537895416},
{"learn":[0.601576828],"iteration":43,"passed_time":0.145440684,"remaining_time":0.3503798296},
{"learn":[0.5995649616],"iteration":44,"passed_time":0.1488077664,"remaining_time":0.3472181216},
{"learn":[0.5984498062],"iteration":45,"passed_time":0.1520922944,"remaining_time":0.3438608396},
{"learn":[0.5967041333],"iteration":46,"passed_time":0.1553145677,"remaining_time":0.3403702229},
{"learn":[0.5955607428],"iteration":47,"passed_time":0.1585945029,"remaining_time":0.3370133186},
{"learn":[0.5942438955],"iteration":48,"passed_time":0.1618922027,"remaining_time":0.3336961728},
{"learn":[0.5929411902],"iteration":49,"passed_time":0.1651680559,"remaining_time":0.3303361117},
{"learn":[0.5917994922],"iteration":50,"passed_time":0.1684336413,"remaining_time":0.3269594213},
{"learn":[0.5906626273],"iteration":51,"passed_time":0.1717129625,"remaining_time":0.3236128908},
{"learn":[0.5900093502],"iteration":52,"passed_time":0.1749512224,"remaining_time":0.3201937467},
{"learn":[0.5886761788],"iteration":53,"passed_time":0.1782743687,"remaining_time":0.316932211},
{"learn":[0.5879231586],"iteration":54,"passed_time":0.1815840373,"remaining_time":0.3136451553},
{"learn":[0.5864030769],"iteration":55,"passed_time":0.184884241,"remaining_time":0.3103414045},
{"learn":[0.5854783735],"iteration":56,"passed_time":0.1881615682,"remaining_time":0.3070004534},
{"learn":[0.5843058229],"iteration":57,"passed_time":0.1914226537,"remaining_time":0.3036359335},
{"learn":[0.5835337609],"iteration":58,"passed_time":0.1947103197,"remaining_time":0.3003159168},
{"learn":[0.5823807731],"iteration":59,"passed_time":0.1980178403,"remaining_time":0.2970267604},
{"learn":[0.5816966231],"iteration":60,"passed_time":0.2012757439,"remaining_time":0.2936646099},
{"learn":[0.5808527801],"iteration":61,"passed_time":0.204507563,"remaining_time":0.290268799},
{"learn":[0.5802087524],"iteration":62,"passed_time":0.2077509198,"remaining_time":0.2868941274},
{"learn":[0.5791330825],"iteration":63,"passed_time":0.2110605204,"remaining_time":0.2836125742},
{"learn":[0.5780485678],"iteration":64,"passed_time":0.214368181,"remaining_time":0.2803276213},
{"learn":[0.5774708241],"iteration":65,"passed_time":0.2176407312,"remaining_time":0.2769972943},
{"learn":[0.5760815713],"iteration":66,"passed_time":0.2209691654,"remaining_time":0.2737379214},
{"learn":[0.5752906736],"iteration":67,"passed_time":0.2242442127,"remaining_time":0.2704121388},
{"learn":[0.5739591262],"iteration":68,"passed_time":0.2275618841,"remaining_time":0.2671378639},
{"learn":[0.5729428893],"iteration":69,"passed_time":0.2307836414,"remaining_time":0.263752733},
{"learn":[0.570883188],"iteration":70,"passed_time":0.2341276602,"remaining_time":0.2605082417},
{"learn":[0.5696487233],"iteration":71,"passed_time":0.2373840798,"remaining_time":0.2571660865},
{"learn":[0.5690315229],"iteration":72,"passed_time":0.2405900724,"remaining_time":0.2537730901},
{"learn":[0.5677423243],"iteration":73,"passed_time":0.2438900972,"remaining_time":0.2504817214},
{"learn":[0.566861668],"iteration":74,"passed_time":0.2471741042,"remaining_time":0.2471741042},
{"learn":[0.5653621482],"iteration":75,"passed_time":0.2505019954,"remaining_time":0.2439098377},
{"learn":[0.5639300855],"iteration":76,"passed_time":0.2536999952,"remaining_time":0.2405207747},
{"learn":[0.5633192306],"iteration":77,"passed_time":0.256946851,"remaining_time":0.2371817086},
{"learn":[0.5622114225],"iteration":78,"passed_time":0.2602085335,"remaining_time":0.2338583022},
{"learn":[0.5609457526],"iteration":79,"passed_time":0.2634619602,"remaining_time":0.2305292151},
{"learn":[0.5598963288],"iteration":80,"passed_time":0.2667826825,"remaining_time":0.2272593221},
{"learn":[0.5589140046],"iteration":81,"passed_time":0.2700974149,"remaining_time":0.2239832221},
{"learn":[0.5578931538],"iteration":82,"passed_time":0.273330879,"remaining_time":0.2206405891},
{"learn":[0.5565666991],"iteration":83,"passed_time":0.2766246569,"remaining_time":0.2173479447},
{"learn":[0.5556094347],"iteration":84,"passed_time":0.2799000101,"remaining_time":0.2140411842},
{"learn":[0.5550952261],"iteration":85,"passed_time":0.2830958329,"remaining_time":0.2106759687},
{"learn":[0.5542399114],"iteration":86,"passed_time":0.2863714401,"remaining_time":0.2073724222},
{"learn":[0.5534685664],"iteration":87,"passed_time":0.2896361366,"remaining_time":0.2040618235},
{"learn":[0.5526647943],"iteration":88,"passed_time":0.2932996771,"remaining_time":0.2010256214},
{"learn":[0.5516963093],"iteration":89,"passed_time":0.2965668775,"remaining_time":0.1977112517},
{"learn":[0.5504285743],"iteration":90,"passed_time":0.2999267171,"remaining_time":0.1944579814},
{"learn":[0.5496179822],"iteration":91,"passed_time":0.3032044013,"remaining_time":0.1911506008},
{"learn":[0.5487405298],"iteration":92,"passed_time":0.3065353714,"remaining_time":0.187876518},
{"learn":[0.5480479466],"iteration":93,"passed_time":0.3111152508,"remaining_time":0.1853452558},
{"learn":[0.5469132052],"iteration":94,"passed_time":0.314442109,"remaining_time":0.1820454316},
{"learn":[0.5462923174],"iteration":95,"passed_time":0.3178129834,"remaining_time":0.1787698032},
{"learn":[0.5452610521],"iteration":96,"passed_time":0.3211466185,"remaining_time":0.1754718637},
{"learn":[0.5443509988],"iteration":97,"passed_time":0.3244612729,"remaining_time":0.1721631244},
{"learn":[0.5433267867],"iteration":98,"passed_time":0.3277572507,"remaining_time":0.1688446443},
{"learn":[0.542315121],"iteration":99,"passed_time":0.3311104134,"remaining_time":0.1655552067},
{"learn":[0.5407928267],"iteration":100,"passed_time":0.334419854,"remaining_time":0.1622432955},
{"learn":[0.5396667106],"iteration":101,"passed_time":0.3377359604,"remaining_time":0.1589345696},
{"learn":[0.5389621829],"iteration":102,"passed_time":0.3410508029,"remaining_time":0.1556251236},
{"learn":[0.5381904969],"iteration":103,"passed_time":0.3443699052,"remaining_time":0.1523174581},
{"learn":[0.5371637764],"iteration":104,"passed_time":0.3477002834,"remaining_time":0.1490144072},
{"learn":[0.536043805],"iteration":105,"passed_time":0.3510634189,"remaining_time":0.145724438},
{"learn":[0.5346858041],"iteration":106,"passed_time":0.3544304383,"remaining_time":0.1424346621},
{"learn":[0.5332153069],"iteration":107,"passed_time":0.3577902569,"remaining_time":0.1391406554},
{"learn":[0.5313789454],"iteration":108,"passed_time":0.3611868217,"remaining_time":0.1358592632},
{"learn":[0.530500396],"iteration":109,"passed_time":0.3645132569,"remaining_time":0.1325502752},
{"learn":[0.5295075252],"iteration":110,"passed_time":0.3677842642,"remaining_time":0.1292214982},
{"learn":[0.5281839344],"iteration":111,"passed_time":0.3710939828,"remaining_time":0.125906887},
{"learn":[0.5264578114],"iteration":112,"passed_time":0.3745660491,"remaining_time":0.1226455205},
{"learn":[0.5245673251],"iteration":113,"passed_time":0.3779746597,"remaining_time":0.1193604189},
{"learn":[0.5237588269],"iteration":114,"passed_time":0.3812332563,"remaining_time":0.1160275128},
{"learn":[0.5227206629],"iteration":115,"passed_time":0.384532348,"remaining_time":0.1127077572},
{"learn":[0.5219228472],"iteration":116,"passed_time":0.3877660161,"remaining_time":0.109369902},
{"learn":[0.5209677824],"iteration":117,"passed_time":0.3911156369,"remaining_time":0.1060652575},
{"learn":[0.5199632969],"iteration":118,"passed_time":0.3944298243,"remaining_time":0.1027506265},
{"learn":[0.5182779393],"iteration":119,"passed_time":0.3978022036,"remaining_time":0.09945055091},
{"learn":[0.5172601231],"iteration":120,"passed_time":0.4010389876,"remaining_time":0.09611678216},
{"learn":[0.5157462261],"iteration":121,"passed_time":0.4043829075,"remaining_time":0.09280919189},
{"learn":[0.5146046514],"iteration":122,"passed_time":0.4087211917,"remaining_time":0.08971928599},
{"learn":[0.5132337372],"iteration":123,"passed_time":0.4121098267,"remaining_time":0.08641012495},
{"learn":[0.5120276377],"iteration":124,"passed_time":0.415481679,"remaining_time":0.08309633581},
{"learn":[0.510572807],"iteration":125,"passed_time":0.4188096652,"remaining_time":0.07977326957},
{"learn":[0.5101830721],"iteration":126,"passed_time":0.4221401764,"remaining_time":0.07645058312},
{"learn":[0.5088014538],"iteration":127,"passed_time":0.4254649486,"remaining_time":0.07312678804},
{"learn":[0.507973365],"iteration":128,"passed_time":0.4287195483,"remaining_time":0.06979155437},
{"learn":[0.5067810109],"iteration":129,"passed_time":0.4320895886,"remaining_time":0.06647532133},
{"learn":[0.5054100898],"iteration":130,"passed_time":0.4353631729,"remaining_time":0.06314427698},
{"learn":[0.5039995156],"iteration":131,"passed_time":0.4386596727,"remaining_time":0.05981722809},
{"learn":[0.5035312681],"iteration":132,"passed_time":0.4418662843,"remaining_time":0.05647914912},
{"learn":[0.5021190256],"iteration":133,"passed_time":0.4452358647,"remaining_time":0.0531624913},
{"learn":[0.5003466946],"iteration":134,"passed_time":0.4485453232,"remaining_time":0.04983836925},
{"learn":[0.4996278119],"iteration":135,"passed_time":0.4518673205,"remaining_time":0.04651575358},
{"learn":[0.4988803807],"iteration":136,"passed_time":0.4551609004,"remaining_time":0.0431904504},
{"learn":[0.4983373224],"iteration":137,"passed_time":0.4584723819,"remaining_time":0.03986716364},
{"learn":[0.4967460268],"iteration":138,"passed_time":0.4617837674,"remaining_time":0.03654403915},
{"learn":[0.4960516506],"iteration":139,"passed_time":0.4650569557,"remaining_time":0.03321835398},
{"learn":[0.4948098827],"iteration":140,"passed_time":0.4683836099,"remaining_time":0.02989682616},
{"learn":[0.4927884236],"iteration":141,"passed_time":0.4718234789,"remaining_time":0.02658160444},
{"learn":[0.49159109],"iteration":142,"passed_time":0.4751259896,"remaining_time":0.02325791557},
{"learn":[0.4902999426],"iteration":143,"passed_time":0.4784559137,"remaining_time":0.01993566307},
{"learn":[0.4896534039],"iteration":144,"passed_time":0.4817445107,"remaining_time":0.01661187968},
{"learn":[0.4884161734],"iteration":145,"passed_time":0.4851293008,"remaining_time":0.01329121372},
{"learn":[0.4866543568],"iteration":146,"passed_time":0.4885727667,"remaining_time":0.009970872789},
{"learn":[0.4858724891],"iteration":147,"passed_time":0.4918471369,"remaining_time":0.006646582932},
{"learn":[0.4849547082],"iteration":148,"passed_time":0.4951759311,"remaining_time":0.003323328397},
{"learn":[0.4837838412],"iteration":149,"passed_time":0.4985365737,"remaining_time":0}
]}